__init__.py
posix_ish.py
atomicswap/__init__.py
atomicswap/linux.py
atomicswap/macos.py
atomicswap/posix_ish.py
atomicswap/windows.py
atomicswap-0.2.2.dist-info/LICENSE.md
atomicswap-0.2.2.dist-info/METADATA
atomicswap-0.2.2.dist-info/WHEEL
atomicswap-0.2.2.dist-info/top_level.txt
atomicswap-0.2.2.dist-info/RECORD
