Metadata-Version: 2.1
Name: atomicswap
Version: 0.2.2
Summary: A simple API to swap two files on a filesystem atomically
Author-email: Nicko van Someren <nicko@nicko.org>
Project-URL: Homepage, https://github.com/nickovs/atomicswap
Project-URL: Bug Tracker, https://github.com/nickovs/atomicswap/issues
Classifier: Programming Language :: Python :: 3
Classifier: License :: OSI Approved :: MIT License
Classifier: Operating System :: MacOS
Classifier: Operating System :: POSIX :: Linux
Requires-Python: >=3.7
License-File: LICENSE.md
Requires-Dist: pywin32 ; sys_platform == "win32"
